image_ocr/__init__.py
image_ocr/config.py
image_ocr/data_generation.py
image_ocr/datasets.py
image_ocr/detection.py
image_ocr/evaluation.py
image_ocr/pipeline.py
image_ocr/recognition.py
image_ocr/tools.py
image_ocr-0.0.4.dist-info/LICENSE
image_ocr-0.0.4.dist-info/WHEEL
image_ocr-0.0.4.dist-info/METADATA
image_ocr-0.0.4.dist-info/RECORD
