Metadata-Version: 2.1
Name: image-ocr
Version: 0.0.4
Summary: A packaged and flexible version of the CRAFT text detector and Keras CRNN recognition model.
Home-page: https://github.com/geo-tp/image-ocr
License: MIT
Author: Geo
Author-email: geoffrey.menon38@gmail.com
Requires-Python: >=3.9
Classifier: License :: OSI Approved :: MIT License
Classifier: Operating System :: MacOS
Classifier: Operating System :: Microsoft :: Windows
Classifier: Operating System :: POSIX :: Linux
Classifier: Operating System :: Unix
Classifier: Programming Language :: Python :: 3
Classifier: Programming Language :: Python :: 3 :: Only
Classifier: Programming Language :: Python :: 3.10
Classifier: Programming Language :: Python :: 3.9
Requires-Dist: editdistance
Requires-Dist: efficientnet
Requires-Dist: essential_generators
Requires-Dist: fonttools
Requires-Dist: imgaug
Requires-Dist: pyclipper
Requires-Dist: shapely
Requires-Dist: tqdm
Requires-Dist: validators
Project-URL: Repository, https://github.com/geo-tp/image-ocr
